setup.cfg
setup.py
recipe/__init__.py
recipe/redis.py
sorinaso.recipe.redis.egg-info/PKG-INFO
sorinaso.recipe.redis.egg-info/SOURCES.txt
sorinaso.recipe.redis.egg-info/dependency_links.txt
sorinaso.recipe.redis.egg-info/entry_points.txt
sorinaso.recipe.redis.egg-info/not-zip-safe
sorinaso.recipe.redis.egg-info/requires.txt
sorinaso.recipe.redis.egg-info/top_level.txt