Metadata-Version: 1.1
Name: sorinaso.recipe.redis
Version: 0.0.3
Summary: Redis recipe for buildout
Home-page: https://github.com/sorinaso/sorinaso.recipe.redis
Author: Alejandro Souto
Author-email: sorinaso@gmail.com
License: MIT
Keywords: buildout redis
Platform: UNKNOWN
Classifier: Framework :: Buildout
Classifier: License :: OSI Approved :: MIT License
Classifier: Programming Language :: Python :: 2.7
